envcfg/__init__.py
envcfg/_hook.py
envcfg/json/__init__.py
envcfg/raw/__init__.py
envcfg/smart/__init__.py
python_envcfg-0.2.0.dist-info/DESCRIPTION.rst
python_envcfg-0.2.0.dist-info/METADATA
python_envcfg-0.2.0.dist-info/RECORD
python_envcfg-0.2.0.dist-info/WHEEL
python_envcfg-0.2.0.dist-info/metadata.json
python_envcfg-0.2.0.dist-info/top_level.txt
