Metadata-Version: 2.0
Name: python-envcfg
Version: 0.2.0
Summary: Accessing environment variables with a magic module.
Home-page: https://github.com/tonyseek/python-envcfg
Author: Jiangge Zhang
Author-email: tonyseek@gmail.com
License: MIT
Keywords: env,config,12-factor
Platform: Any
Classifier: Development Status :: 3 - Alpha
Classifier: License :: OSI Approved :: MIT License
Classifier: Operating System :: OS Independent
Classifier: Programming Language :: Python
Classifier: Programming Language :: Python :: 2.7
Classifier: Programming Language :: Python :: 3.3
Classifier: Programming Language :: Python :: 3.4
Classifier: Topic :: Software Development :: Libraries
